test/__init__.py
test/wsgi_bottle_test.py
test/wsgi_flask_test.py
test/wsgi_server_test.py
viola/__init__.py
viola/exception.py
viola/core/__init__.py
viola/core/epoll.py
viola/core/event_loop.py
viola/core/scheduler.py
viola/core/server.py
viola/core/stream.py
viola/http/__init__.py
viola/http/keepalive.py
viola/http/parser.py
viola/http/wrapper.py
viola/wsgi/__init__.py
viola/wsgi/server.py
viola/wsgi/stream.py
viola-0.3.8.dist-info/LICENSE
viola-0.3.8.dist-info/METADATA
viola-0.3.8.dist-info/WHEEL
viola-0.3.8.dist-info/top_level.txt
viola-0.3.8.dist-info/RECORD
