Metadata-Version: 2.1
Name: viola
Version: 0.3.8
Summary: viola is a lightweight and efficient WSGI server.
Home-page: https://github.com/prprprus/viola
Author: prprprus
Author-email: huangzongzhuan@gmail.com
License: UNKNOWN
Platform: UNKNOWN
Classifier: Programming Language :: Python :: 3
Classifier: License :: OSI Approved :: MIT License
Classifier: Operating System :: OS Independent
